dialog_yml/__init__.py
dialog_yml/core.py
dialog_yml/decorators.py
dialog_yml/exceptions.py
dialog_yml/middleware.py
dialog_yml/reader.py
dialog_yml/states.py
dialog_yml/utils.py
dialog_yml/models/__init__.py
dialog_yml/models/base.py
dialog_yml/models/dialog.py
dialog_yml/models/window.py
dialog_yml/models/funcs/__init__.py
dialog_yml/models/funcs/func.py
dialog_yml/models/widgets/__init__.py
dialog_yml/models/widgets/calendars/__init__.py
dialog_yml/models/widgets/calendars/calendar.py
dialog_yml/models/widgets/counters/__init__.py
dialog_yml/models/widgets/counters/counter.py
dialog_yml/models/widgets/inputs/__init__.py
dialog_yml/models/widgets/inputs/input.py
dialog_yml/models/widgets/kbd/__init__.py
dialog_yml/models/widgets/kbd/keyboard.py
dialog_yml/models/widgets/medias/__init__.py
dialog_yml/models/widgets/medias/media.py
dialog_yml/models/widgets/scrolls/__init__.py
dialog_yml/models/widgets/scrolls/scroll.py
dialog_yml/models/widgets/selects/__init__.py
dialog_yml/models/widgets/selects/select.py
dialog_yml/models/widgets/texts/__init__.py
dialog_yml/models/widgets/texts/text.py
dialog_yml-0.1.3.dist-info/licenses/LICENSE
dialog_yml-0.1.3.dist-info/METADATA
dialog_yml-0.1.3.dist-info/WHEEL
dialog_yml-0.1.3.dist-info/top_level.txt
dialog_yml-0.1.3.dist-info/RECORD
