Metadata-Version: 2.4
Name: dialog-yml
Version: 0.1.3
Summary: A Python library that enables building aiogram-dialog applications using YAML configuration files
Author-email: Mikhail Vlasenko <ya@smkthat.ru>
Maintainer-email: Mikhail Vlasenko <ya@smkthat.ru>
License-Expression: MIT
Project-URL: Homepage, https://github.com/smkthat/dialog-yml
Project-URL: Repository, https://github.com/smkthat/dialog-yml
Project-URL: Issues, https://github.com/smkthat/dialog-yml/issues
Keywords: aiogram,aiogram-dialog,yaml,telegram,bot,dialogs
Classifier: Development Status :: 4 - Beta
Classifier: Intended Audience :: Developers
Classifier: Programming Language :: Python :: 3
Classifier: Programming Language :: Python :: 3.13
Classifier: Topic :: Software Development :: Libraries :: Python Modules
Classifier: Framework :: AsyncIO
Classifier: Operating System :: OS Independent
Requires-Python: >=3.13
License-File: LICENSE
Requires-Dist: aiogram>=3.24.0
Requires-Dist: aiogram-dialog~=2.4
Requires-Dist: babel>=2.17.0
Requires-Dist: pydantic>=2.12.5
Requires-Dist: python-dotenv>=1.2.1
Requires-Dist: pyyaml>=6.0.3
Requires-Dist: pyyaml-include>=2.2
Dynamic: license-file
